ambient_utils/__init__.py
ambient_utils/classifier.py
ambient_utils/dataset.py
ambient_utils/diffusers.py
ambient_utils/dist.py
ambient_utils/eval.py
ambient_utils/loss.py
ambient_utils/noise.py
ambient_utils/url.py
ambient_utils/utils.py
ambient_utils/torch_utils/__init__.py
ambient_utils/torch_utils/persistence.py
ambient_utils-1.0.2.dist-info/licenses/LICENSE
ambient_utils-1.0.2.dist-info/METADATA
ambient_utils-1.0.2.dist-info/WHEEL
ambient_utils-1.0.2.dist-info/top_level.txt
ambient_utils-1.0.2.dist-info/RECORD
