Metadata-Version: 2.4
Name: ambient_utils
Version: 1.0.2
Summary: Utility functions for learning generative models from corrupted data.
Home-page: https://github.com/giannisdaras/ambient_utils
Author: giannisdaras
Author-email: daras.giannhs@gmail.com
License: GPL-3.0
Classifier: Programming Language :: Python :: 3
Classifier: Operating System :: OS Independent
Classifier: Topic :: Scientific/Engineering :: Artificial Intelligence
Classifier: Intended Audience :: Science/Research
Requires-Python: >=3.6
License-File: LICENSE
Requires-Dist: numpy
Requires-Dist: scipy
Requires-Dist: torch
Requires-Dist: Pillow
Provides-Extra: all
Requires-Dist: wandb; extra == "all"
Requires-Dist: seaborn; extra == "all"
Requires-Dist: torchvision; extra == "all"
Requires-Dist: diffusers; extra == "all"
Requires-Dist: s3fs; extra == "all"
Requires-Dist: webdataset; extra == "all"
Requires-Dist: datasets; extra == "all"
Requires-Dist: imagecorruptions; extra == "all"
Provides-Extra: dev
Requires-Dist: pytest; extra == "dev"
Requires-Dist: black; extra == "dev"
Requires-Dist: flake8; extra == "dev"
Provides-Extra: docs
Requires-Dist: sphinx; extra == "docs"
Requires-Dist: sphinx-rtd-theme; extra == "docs"
Dynamic: author
Dynamic: author-email
Dynamic: classifier
Dynamic: description
Dynamic: description-content-type
Dynamic: home-page
Dynamic: license
Dynamic: license-file
Dynamic: provides-extra
Dynamic: requires-dist
Dynamic: requires-python
Dynamic: summary
